{
    "Fluid": [
        {
            "Id": "29636f04-826b-48f7-8dbc-4e814485dd39",
            "Position": {
                "x": 0,
                "y": 0,
                "z": 0
            },
            "Velocity": {
                "x": 0,
                "y": 0,
                "z": 0
            },
            "Acceleration": {
                "x": 0,
                "y": 0,
                "z": 0
            },
            "Elasticity": 0.6,
            "Radius": 0.15,
            "MassMultiplier": 100,
            "Mass": 0.1,
            "Color": {
                "R": 255,
                "G": 255,
                "B": 255,
                "A": 255
            },
            "Heat": 0
        },
        {
            "Id": "97415841-59d5-4f90-9ecf-a48fed00edba",
            "Position": {
                "x": 1,
                "y": 0,
                "z": 0
            },
            "Velocity": {
                "x": 0,
                "y": 4,
                "z": 0
            },
            "Acceleration": {
                "x": 0,
                "y": 0,
                "z": 0
            },
            "Elasticity": 0.6,
            "Radius": 0.1,
            "MassMultiplier": 100,
            "Mass": 0.0005,
            "Color": {
                "R": 255,
                "G": 255,
                "B": 255,
                "A": 255
            },
            "Heat": 0
        },
        {
            "Id": "6917da7b-de8e-4426-845e-73959b075c5e",
            "Position": {
                "x": -1,
                "y": 0,
                "z": 0
            },
            "Velocity": {
                "x": 0,
                "y": -4,
                "z": 0
            },
            "Acceleration": {
                "x": 0,
                "y": 0,
                "z": 0
            },
            "Elasticity": 0.6,
            "Radius": 0.1,
            "MassMultiplier": 100,
            "Mass": 0.0005,
            "Color": {
                "R": 255,
                "G": 255,
                "B": 255,
                "A": 255
            },
            "Heat": 0
        }
    ],
    "Config": {
        "FullScreen": false,
        "WindowWidth": 1600,
        "WindowHeight": 1280,
        "SidebarWidth": 0,
        "ViewportX": 0,
        "ViewportY": 0,
        "GameX": 20,
        "GameY": 20,
        "GameZ": 20,
        "TargetFPS": 60,
        "IsResizable": true,
        "UnitNumber": 3,
        "UnitRadius": 1,
        "UnitMassMultiplier": 100,
        "UnitInitialSpacing": 5,
        "ShowVectors": true,
        "UnitElasticity": 0.6,
        "WallElasticity": 0.5,
        "ApplyGravity": false,
        "Gravity": -9.81,
        "ShowOctree": true,
        "ShowTrail": false,
        "ShouldBeProfiled": true,
        "SetRandomRadius": false,
        "RadiusMin": 0.1,
        "RadiusMax": 1,
        "SetRandomMassMultiplier": false,
        "MassMultiplierMin": 1,
        "MassMultiplierMax": 10,
        "SetRandomElasticity": false,
        "ElasticityMin": 0.5,
        "ElasticityMax": 0.7,
        "ShowOverlay": false,
        "SetRandomColor": true,
        "ShowSpeedColor": false,
        "UnitsEmitGravity": true,
        "UnitRadiusMultiplier": 0.01,
        "ShowClusterColor": false,
        "OctreeMaxLevel": 6,
        "MaxUnitNumberPerLevel": 1,
        "Frametime": 0.001
    },
    "IsPause": false,
    "WorldBoundray": {
        "Min": {
            "x": -10,
            "y": -10,
            "z": -10
        },
        "Max": {
            "x": 10,
            "y": 10,
            "z": 10
        }
    },
    "WorldCenter": {
        "x": 0,
        "y": 0,
        "z": 0
    }
}
